alive_checks/__init__.py
alive_checks/apps.py
alive_checks/checks/__init__.py
alive_checks/checks/elasticsearch.py
alive_checks/tests/__init__.py
alive_checks/tests/test_elasticsearch_check.py
django_alive_checks-0.2.dist-info/LICENSE
django_alive_checks-0.2.dist-info/METADATA
django_alive_checks-0.2.dist-info/WHEEL
django_alive_checks-0.2.dist-info/top_level.txt
django_alive_checks-0.2.dist-info/RECORD
