Metadata-Version: 2.1
Name: django-alive-checks
Version: 0.2
Summary: Additional health checks for django-alive
Home-page: https://github.com/PetrDlouhy/django-alive-checks
Author: Your Name
Author-email: your.email@example.com
Classifier: Development Status :: 3 - Alpha
Classifier: Framework :: Django
Classifier: Intended Audience :: Developers
Classifier: License :: OSI Approved :: MIT License
Classifier: Programming Language :: Python :: 3
Classifier: Programming Language :: Python :: 3.8
License-File: LICENSE
Requires-Dist: Django (>=3.2)
Requires-Dist: django-alive
Provides-Extra: elasticsearch
Requires-Dist: elasticsearch (>=7.0.0) ; extra == 'elasticsearch'
